test_average/__init__.py
test_average/average.py
hellowpkg-1.0.4.dist-info/METADATA
hellowpkg-1.0.4.dist-info/WHEEL
hellowpkg-1.0.4.dist-info/top_level.txt
hellowpkg-1.0.4.dist-info/RECORD
