Metadata-Version: 2.1
Name: hellowpkg
Version: 1.0.4
Summary: A test package to demonstrate malicious pip packages
Home-page: UNKNOWN
Author: Pattrick Bateman
Author-email: patbateman@ecorp.com
License: UNKNOWN
Platform: UNKNOWN
Classifier: Programming Language :: Python :: 3
Classifier: License :: OSI Approved :: MIT License
Classifier: Operating System :: OS Independent
Requires-Python: >=3.6
